spaceship_dns_updater/__init__.py
spaceship_dns_updater/config.py
spaceship_dns_updater/config_model.py
spaceship_dns_updater/updater.py
spaceship_dns_updater/utils.py
spaceship_dns_updater-0.1.0.dist-info/entry_points.txt
spaceship_dns_updater-0.1.0.dist-info/METADATA
spaceship_dns_updater-0.1.0.dist-info/WHEEL
spaceship_dns_updater-0.1.0.dist-info/RECORD
