Metadata-Version: 2.3
Name: spaceship-dns-updater
Version: 0.1.0
Summary: Script to update DNS records using the spaceship API
Author: Benjamin Wiessneth
Author-email: b.wiessneth@gmail.com
Requires-Python: >=3.12,<4.0
Classifier: Programming Language :: Python :: 3
Classifier: Programming Language :: Python :: 3.12
Classifier: Programming Language :: Python :: 3.13
Requires-Dist: click (>=8.2.1,<9.0.0)
Requires-Dist: loguru (>=0.7.3,<0.8.0)
Requires-Dist: pydantic (>=2.11.7,<3.0.0)
Requires-Dist: pyyaml (>=6.0.2,<7.0.0)
Requires-Dist: requests (>=2.32.4,<3.0.0)
Requires-Dist: spaceship-api (>=0.1.0,<0.2.0)
